MANIFEST.in
setup.py
data/hinnavaatlus.csv
data/hinnavaatlus_simple.csv
data/hinnavaatlus_test.csv
definitions/hinnavaatlus.def
estnltk_textclassifier.egg-info/PKG-INFO
estnltk_textclassifier.egg-info/SOURCES.txt
estnltk_textclassifier.egg-info/dependency_links.txt
estnltk_textclassifier.egg-info/requires.txt
estnltk_textclassifier.egg-info/top_level.txt
models/empty
textclassifier/__init__.py
textclassifier/analyzer.py
textclassifier/classifier.py
textclassifier/classify.py
textclassifier/clfbase.py
textclassifier/featureextractor.py
textclassifier/merge.py
textclassifier/paths.py
textclassifier/reportgenerator.py
textclassifier/retrain.py
textclassifier/settings.py
textclassifier/synunifier.py
textclassifier/test.py
textclassifier/train.py
textclassifier/utils.py
textclassifier/tests/__init__.py
textclassifier/tests/definition.def
textclassifier/tests/definition_duplicate.def
textclassifier/tests/definition_invalid_section.def
textclassifier/tests/definition_nosection.def
textclassifier/tests/extra.xlsx
textclassifier/tests/merge.def
textclassifier/tests/original.xlsx
textclassifier/tests/result.xlsx
textclassifier/tests/test_analyzer.py
textclassifier/tests/test_classifier.py
textclassifier/tests/test_featureextractor.py
textclassifier/tests/test_merge.py
textclassifier/tests/test_report.py
textclassifier/tests/test_retrain.py
textclassifier/tests/test_settings.py
textclassifier/tests/test_synunifier.py
textclassifier/tests/test_user_trains_and_uses_model.py
textclassifier/tests/testsynonyms.txt
textclassifier/tests/weather.csv
textclassifier/tests/weather.def
textclassifier/tests/weather.txt
textclassifier/tests/weather.xlsx